mcp_transcoder/main.py
mcp_transcoder-0.1.1.dist-info/licenses/LICENSE
mcp_transcoder-0.1.1.dist-info/METADATA
mcp_transcoder-0.1.1.dist-info/WHEEL
mcp_transcoder-0.1.1.dist-info/entry_points.txt
mcp_transcoder-0.1.1.dist-info/top_level.txt
mcp_transcoder-0.1.1.dist-info/RECORD
