Metadata-Version: 2.4
Name: mcp-transcoder
Version: 0.1.1
Summary: Bridge STDIO-based MCP clients to StreamableHTTP MCP servers with header, TLS, and timeout options.
Project-URL: Homepage, https://github.com/post-class/mcp-transcoder
Project-URL: Repository, https://github.com/post-class/mcp-transcoder
Requires-Python: >=3.11
License-File: LICENSE
Requires-Dist: mcp>=1.18.0
Dynamic: license-file
